[{"region": "BR", "id": 4016987}, {"region": "BR", "id": 541466}, {"region": "BR", "id": 1512623}, {"region": "BR", "id": 447066}, {"region": "BR", "id": 1511375}, {"region": "BR", "id": 528221}, {"region": "BR", "id": 1680691}, {"region": "BR", "id": 480680}, {"region": "BR", "id": 740475}, {"region": "BR", "id": 476823}, {"region": "BR", "id": 2006828}, {"region": "BR", "id": 649667}, {"region": "BR", "id": 3352432}, {"region": "BR", "id": 7403758}, {"region": "BR", "id": 1734587}, {"region": "BR", "id": 1334123}, {"region": "BR", "id": 2848552}, {"region": "BR", "id": 4151111}, {"region": "BR", "id": 2112757}, {"region": "BR", "id": 454250}, {"region": "BR", "id": 3781882}, {"region": "BR", "id": 4151111}, {"region": "BR", "id": 1680691}, {"region": "BR", "id": 860797}, {"region": "BR", "id": 478125}, {"region": "BR", "id": 1070364}, {"region": "BR", "id": 751044}, {"region": "BR", "id": 3397084}, {"region": "BR", "id": 645522}, {"region": "EUNE", "id": 42345315}, {"region": "EUNE", "id": 25415641}, {"region": "EUNE", "id": 29019098}, {"region": "EUNE", "id": 20276771}, {"region": "EUNE", "id": 37394326}, {"region": "EUNE", "id": 35324998}, {"region": "EUNE", "id": 41606507}, {"region": "EUNE", "id": 28445903}, {"region": "EUNE", "id": 30965881}, {"region": "EUNE", "id": 37212144}, {"region": "EUNE", "id": 18989398}, {"region": "EUNE", "id": 19391583}, {"region": "EUNE", "id": 18989398}, {"region": "EUNE", "id": 30463011}, {"region": "EUNE", "id": 20116531}, {"region": "EUNE", "id": 38133327}, {"region": "EUNE", "id": 21744058}, {"region": "EUNE", "id": 19835940}, {"region": "EUNE", "id": 21744058}, {"region": "EUNE", "id": 19774964}, {"region": "EUNE", "id": 19835940}, {"region": "EUNE", "id": 31456244}, {"region": "EUNE", "id": 43239321}, {"region": "EUNE", "id": 31553906}, {"region": "EUNE", "id": 34595690}, {"region": "EUNE", "id": 33887716}, {"region": "EUNE", "id": 20107818}, {"region": "EUNE", "id": 33132995}, {"region": "EUNE", "id": 34595690}, {"region": "EUNE", "id": 24204881}, {"region": "EUNE", "id": 36970406}, {"region": "EUNE", "id": 31456244}, {"region": "EUNE", "id": 34283012}, {"region": "EUNE", "id": 23567717}, {"region": "EUNE", "id": 20731568}, {"region": "EUNE", "id": 30905635}, {"region": "EUNE", "id": 34003519}, {"region": "EUNE", "id": 27496255}, {"region": "EUNE", "id": 30938284}, {"region": "EUNE", "id": 32063148}, {"region": "EUNE", "id": 28524976}, {"region": "EUNE", "id": 33273287}, {"region": "EUNE", "id": 23399851}, {"region": "EUNE", "id": 25573083}, {"region": "EUNE", "id": 31456244}, {"region": "EUNE", "id": 24426452}, {"region": "EUNE", "id": 24305947}, {"region": "EUNE", "id": 30135192}, {"region": "EUNE", "id": 33775981}, {"region": "EUNE", "id": 33406346}, {"region": "EUNE", "id": 28803761}, {"region": "EUNE", "id": 24425086}, {"region": "EUNE", "id": 31456244}, {"region": "EUNE", "id": 23661239}, {"region": "EUNE", "id": 34003519}, {"region": "EUNE", "id": 26285644}, {"region": "EUNE", "id": 26393209}, {"region": "EUW", "id": 19019253}, {"region": "EUW", "id": 28939130}, {"region": "EUW", "id": 28860359}, {"region": "EUW", "id": 20928128}, {"region": "EUW", "id": 29731484}, {"region": "EUW", "id": 39575672}, {"region": "EUW", "id": 321603}, {"region": "EUW", "id": 269901}, {"region": "EUW", "id": 39068382}, {"region": "EUW", "id": 19533678}, {"region": "EUW", "id": 22100314}, {"region": "EUW", "id": 23307645}, {"region": "EUW", "id": 19728390}, {"region": "EUW", "id": 24509655}, {"region": "EUW", "id": 20628692}, {"region": "EUW", "id": 41227079}, {"region": "EUW", "id": 28019004}, {"region": "EUW", "id": 19407104}, {"region": "EUW", "id": 40491420}, {"region": "EUW", "id": 23307645}, {"region": "EUW", "id": 58376874}, {"region": "EUW", "id": 24127007}, {"region": "EUW", "id": 27492710}, {"region": "EUW", "id": 23307645}, {"region": "EUW", "id": 39575672}, {"region": "EUW", "id": 58769845}, {"region": "EUW", "id": 62577761}, {"region": "EUW", "id": 19280115}, {"region": "EUW", "id": 19174724}, {"region": "EUW", "id": 42028948}, {"region": "EUW", "id": 25225105}, {"region": "EUW", "id": 19280115}, {"region": "EUW", "id": 19315146}, {"region": "EUW", "id": 19315146}, {"region": "EUW", "id": 19538171}, {"region": "EUW", "id": 20372637}, {"region": "EUW", "id": 44387851}, {"region": "EUW", "id": 27367927}, {"region": "EUW", "id": 41517773}, {"region": "EUW", "id": 36764060}, {"region": "EUW", "id": 27561798}, {"region": "EUW", "id": 27289765}, {"region": "KR", "id": 3894493}, {"region": "KR", "id": 6976172}, {"region": "KR", "id": 1989344}, {"region": "KR", "id": 7023725}, {"region": "KR", "id": 20661849}, {"region": "KR", "id": 3995804}, {"region": "KR", "id": 3995804}, {"region": "KR", "id": 5912311}, {"region": "KR", "id": 20642189}, {"region": "KR", "id": 5012292}, {"region": "KR", "id": 8580879}, {"region": "KR", "id": 10736154}, {"region": "KR", "id": 6920973}, {"region": "KR", "id": 2726229}, {"region": "KR", "id": 1613320}, {"region": "KR", "id": 9046631}, {"region": "KR", "id": 3200262}, {"region": "KR", "id": 9998564}, {"region": "KR", "id": 2147506}, {"region": "LAN", "id": 175683}, {"region": "LAN", "id": 52696}, {"region": "LAN", "id": 411842}, {"region": "LAN", "id": 83534}, {"region": "LAN", "id": 203629}, {"region": "LAN", "id": 52696}, {"region": "LAN", "id": 161907}, {"region": "LAN", "id": 312167}, {"region": "LAN", "id": 153290}, {"region": "LAN", "id": 104234}, {"region": "LAN", "id": 549055}, {"region": "LAN", "id": 409900}, {"region": "LAN", "id": 162724}, {"region": "LAN", "id": 34810}, {"region": "LAN", "id": 123189}, {"region": "LAN", "id": 21717}, {"region": "LAN", "id": 113420}, {"region": "LAN", "id": 876719}, {"region": "LAN", "id": 511014}, {"region": "LAN", "id": 27778}, {"region": "LAN", "id": 1282613}, {"region": "LAN", "id": 285200}, {"region": "LAN", "id": 34105}, {"region": "LAN", "id": 525156}, {"region": "LAN", "id": 2700145}, {"region": "LAN", "id": 190501}, {"region": "LAN", "id": 195242}, {"region": "LAN", "id": 650877}, {"region": "LAN", "id": 1212342}, {"region": "LAN", "id": 2700145}, {"region": "LAN", "id": 21868}, {"region": "LAN", "id": 220019}, {"region": "LAN", "id": 151774}, {"region": "LAN", "id": 430701}, {"region": "LAN", "id": 5890167}, {"region": "LAN", "id": 52285}, {"region": "LAN", "id": 1564347}, {"region": "LAN", "id": 67121}, {"region": "LAN", "id": 1020434}, {"region": "LAN", "id": 50219}, {"region": "LAN", "id": 95427}, {"region": "LAN", "id": 366463}, {"region": "LAN", "id": 84591}, {"region": "LAN", "id": 298946}, {"region": "LAN", "id": 48146}, {"region": "LAN", "id": 37619}, {"region": "LAN", "id": 511014}, {"region": "LAN", "id": 296278}, {"region": "LAN", "id": 538692}, {"region": "LAN", "id": 511014}, {"region": "LAN", "id": 525156}, {"region": "LAS", "id": 64527}, {"region": "LAS", "id": 53163}, {"region": "LAS", "id": 951546}, {"region": "LAS", "id": 125511}, {"region": "LAS", "id": 1190213}, {"region": "LAS", "id": 114549}, {"region": "LAS", "id": 148631}, {"region": "LAS", "id": 148463}, {"region": "LAS", "id": 61543}, {"region": "LAS", "id": 36709}, {"region": "LAS", "id": 298937}, {"region": "LAS", "id": 120459}, {"region": "LAS", "id": 430017}, {"region": "LAS", "id": 99622}, {"region": "LAS", "id": 80182}, {"region": "LAS", "id": 73804}, {"region": "LAS", "id": 1611813}, {"region": "LAS", "id": 86040}, {"region": "LAS", "id": 70175}, {"region": "LAS", "id": 590119}, {"region": "LAS", "id": 120381}, {"region": "LAS", "id": 778126}, {"region": "LAS", "id": 36074}, {"region": "LAS", "id": 144319}, {"region": "LAS", "id": 103919}, {"region": "LAS", "id": 312286}, {"region": "LAS", "id": 99854}, {"region": "LAS", "id": 85478}, {"region": "LAS", "id": 68135}, {"region": "LAS", "id": 36074}, {"region": "LAS", "id": 120381}, {"region": "LAS", "id": 51722}, {"region": "LAS", "id": 141066}, {"region": "LAS", "id": 85478}, {"region": "LAS", "id": 778126}, {"region": "LAS", "id": 260452}, {"region": "LAS", "id": 493532}, {"region": "LAS", "id": 107325}, {"region": "LAS", "id": 312286}, {"region": "LAS", "id": 140536}, {"region": "LAS", "id": 164539}, {"region": "LAS", "id": 148631}, {"region": "LAS", "id": 37150}, {"region": "LAS", "id": 32705}, {"region": "LAS", "id": 249684}, {"region": "LAS", "id": 83935}, {"region": "LAS", "id": 36709}, {"region": "LAS", "id": 182281}, {"region": "LAS", "id": 257184}, {"region": "LAS", "id": 199826}, {"region": "LAS", "id": 94091}, {"region": "LAS", "id": 52879}, {"region": "LAS", "id": 1073599}, {"region": "LAS", "id": 94091}, {"region": "LAS", "id": 131500}, {"region": "LAS", "id": 493532}, {"region": "LAS", "id": 51722}, {"region": "LAS", "id": 72794}, {"region": "LAS", "id": 285409}, {"region": "LAS", "id": 2631149}, {"region": "LAS", "id": 56339}, {"region": "NA", "id": 22217054}, {"region": "NA", "id": 40848171}, {"region": "NA", "id": 20481240}, {"region": "NA", "id": 25976023}, {"region": "NA", "id": 19339669}, {"region": "NA", "id": 24382501}, {"region": "NA", "id": 20185262}, {"region": "NA", "id": 37790814}, {"region": "NA", "id": 19339669}, {"region": "NA", "id": 44960842}, {"region": "NA", "id": 18978495}, {"region": "NA", "id": 443949}, {"region": "NA", "id": 44910308}, {"region": "NA", "id": 19786612}, {"region": "NA", "id": 37790814}, {"region": "NA", "id": 32245110}, {"region": "NA", "id": 21385344}, {"region": "NA", "id": 22048840}, {"region": "NA", "id": 21251444}, {"region": "NA", "id": 36451262}, {"region": "NA", "id": 19239920}, {"region": "NA", "id": 22355968}, {"region": "NA", "id": 20579874}, {"region": "NA", "id": 21764938}, {"region": "NA", "id": 30616977}, {"region": "NA", "id": 29311640}, {"region": "NA", "id": 21197261}, {"region": "OCE", "id": 237121}, {"region": "OCE", "id": 634181}, {"region": "OCE", "id": 446841}, {"region": "OCE", "id": 461729}, {"region": "OCE", "id": 553604}, {"region": "OCE", "id": 3940225}, {"region": "OCE", "id": 553604}, {"region": "OCE", "id": 563724}, {"region": "OCE", "id": 3940225}, {"region": "OCE", "id": 478945}, {"region": "OCE", "id": 634181}, {"region": "OCE", "id": 553604}, {"region": "OCE", "id": 434313}, {"region": "OCE", "id": 283050}, {"region": "OCE", "id": 553604}, {"region": "OCE", "id": 312421}, {"region": "OCE", "id": 3940225}, {"region": "OCE", "id": 1271175}, {"region": "OCE", "id": 383070}, {"region": "OCE", "id": 3940225}, {"region": "OCE", "id": 1374635}, {"region": "OCE", "id": 401459}, {"region": "OCE", "id": 634181}, {"region": "OCE", "id": 401459}, {"region": "OCE", "id": 280489}, {"region": "OCE", "id": 473675}, {"region": "OCE", "id": 311127}, {"region": "OCE", "id": 353556}, {"region": "OCE", "id": 279114}, {"region": "OCE", "id": 351275}, {"region": "OCE", "id": 752735}, {"region": "RU", "id": 103605}, {"region": "RU", "id": 240959}, {"region": "RU", "id": 255784}, {"region": "RU", "id": 4610132}, {"region": "RU", "id": 333201}, {"region": "RU", "id": 83881}, {"region": "RU", "id": 965196}, {"region": "RU", "id": 615765}, {"region": "RU", "id": 300622}, {"region": "RU", "id": 1100191}, {"region": "RU", "id": 933970}, {"region": "RU", "id": 282441}, {"region": "RU", "id": 958831}, {"region": "RU", "id": 97730}, {"region": "RU", "id": 61375}, {"region": "RU", "id": 83881}, {"region": "RU", "id": 212460}, {"region": "RU", "id": 615765}, {"region": "RU", "id": 317073}, {"region": "RU", "id": 71444}, {"region": "RU", "id": 941001}, {"region": "RU", "id": 297823}, {"region": "RU", "id": 2141366}, {"region": "RU", "id": 1940133}, {"region": "RU", "id": 253326}, {"region": "RU", "id": 1940133}, {"region": "RU", "id": 3060142}, {"region": "RU", "id": 300622}, {"region": "RU", "id": 262083}, {"region": "TR", "id": 3791366}, {"region": "TR", "id": 1364645}, {"region": "TR", "id": 466626}, {"region": "TR", "id": 467314}, {"region": "TR", "id": 1410849}, {"region": "TR", "id": 814613}, {"region": "TR", "id": 3941010}, {"region": "TR", "id": 459898}, {"region": "TR", "id": 322097}, {"region": "TR", "id": 1452396}, {"region": "TR", "id": 2837869}, {"region": "TR", "id": 1823114}, {"region": "TR", "id": 500719}, {"region": "TR", "id": 833215}, {"region": "TR", "id": 2053848}, {"region": "TR", "id": 236078}, {"region": "TR", "id": 1054762}, {"region": "TR", "id": 277093}, {"region": "TR", "id": 388080}, {"region": "TR", "id": 1073754}, {"region": "TR", "id": 283117}, {"region": "TR", "id": 4352914}, {"region": "TR", "id": 171287}, {"region": "TR", "id": 421224}, {"region": "TR", "id": 652070}, {"region": "TR", "id": 2482730}, {"region": "TR", "id": 1990536}, {"region": "TR", "id": 1773381}, {"region": "TR", "id": 2543456}, {"region": "TR", "id": 190690}, {"region": "TR", "id": 2044011}, {"region": "TR", "id": 2451068}, {"region": "TR", "id": 3303025}, {"region": "TR", "id": 1774731}, {"region": "TR", "id": 3052382}, {"region": "TR", "id": 3495223}, {"region": "TR", "id": 3801071}, {"region": "TR", "id": 642048}, {"region": "TR", "id": 2311974}, {"region": "TR", "id": 1830131}]